kawasemi/__about__.py
kawasemi/__init__.py
kawasemi/cli.py
kawasemi/django.py
kawasemi/exceptions.py
kawasemi/kawasemi.py
kawasemi/types.py
kawasemi/backends/__init__.py
kawasemi/backends/base.py
kawasemi/backends/github.py
kawasemi/backends/hipchat.py
kawasemi/backends/slack.py
kawasemi/backends/twitter.py
kawasemi/backends/yo.py
tests/core/__init__.py
tests/core/test_kawasemi.py
tests/core/backends/__init__.py
tests/core/backends/test_base.py
tests/core/backends/test_github.py
tests/core/backends/test_hipchat.py
tests/core/backends/test_slack.py
tests/core/backends/test_twitter.py
tests/core/backends/test_yo.py
tests/django/__init__.py
tests/django/runtests.py
tests/django/settings.py
tests/django/test_django.py
kawasemi-3.0.0.dist-info/LICENSE
kawasemi-3.0.0.dist-info/METADATA
kawasemi-3.0.0.dist-info/WHEEL
kawasemi-3.0.0.dist-info/entry_points.txt
kawasemi-3.0.0.dist-info/top_level.txt
kawasemi-3.0.0.dist-info/RECORD
