Metadata-Version: 2.1
Name: kawasemi
Version: 3.0.0
Summary: A Python library for sending notifications to services such as Slack, HipChat, Twitter, and so on
Home-page: https://github.com/ymyzk/kawasemi
Author: Yusuke Miyazaki
Author-email: miyazaki.dev@gmail.com
License: MIT
Platform: UNKNOWN
Classifier: Development Status :: 5 - Production/Stable
Classifier: Environment :: Web Environment
Classifier: Framework :: Django
Classifier: Intended Audience :: Developers
Classifier: License :: OSI Approved :: MIT License
Classifier: Operating System :: OS Independent
Classifier: Programming Language :: Python
Classifier: Programming Language :: Python :: 2
Classifier: Programming Language :: Python :: 2.7
Classifier: Programming Language :: Python :: 3
Classifier: Programming Language :: Python :: 3.5
Classifier: Programming Language :: Python :: 3.6
Classifier: Programming Language :: Python :: 3.7
Classifier: Programming Language :: Python :: 3.8
Classifier: Programming Language :: Python :: Implementation :: PyPy
Classifier: Topic :: Internet :: WWW/HTTP
Requires-Python: >=2.7, !=3.0.*, !=3.1.*, !=3.2.*, !=3.3.*, !=3.4.*, <4
Requires-Dist: click (<7.0,>=6.0)
Requires-Dist: requests (>=2.7.0)
Requires-Dist: requests-oauthlib (>=0.5.0)
Requires-Dist: six (>=1.9.0)
Requires-Dist: typing ; python_version < "3.5"
Provides-Extra: docs
Requires-Dist: Sphinx (<1.7,>=1.6) ; extra == 'docs'
Requires-Dist: sphinx-rtd-theme (<0.3,>=0.2) ; extra == 'docs'
Provides-Extra: test
Requires-Dist: coverage (<5.0.0,>=4.3.4) ; extra == 'test'
Requires-Dist: coveralls (<2.0,>=1.1) ; extra == 'test'
Requires-Dist: flake8 (<4.0.0,>=3.3.0) ; extra == 'test'
Requires-Dist: pytest (<4.0.0,>=3.0.0) ; extra == 'test'
Requires-Dist: pytest-cov (<3.0.0,>=2.4.0) ; extra == 'test'
Requires-Dist: pytest-mock (<2.0.0,>=1.5.0) ; extra == 'test'
Requires-Dist: mypy ; (python_version >= "3.3") and extra == 'test'
